locache.py
locache-4.0.2.dist-info/LICENCE.md
locache-4.0.2.dist-info/METADATA
locache-4.0.2.dist-info/WHEEL
locache-4.0.2.dist-info/top_level.txt
locache-4.0.2.dist-info/RECORD
