Metadata-Version: 2.1
Name: locache
Version: 4.0.2
Summary: Cache expensive function calls to disk.
Author-email: John Gardner <gardner.john97@gmail.com>
Project-URL: Homepage, https://github.com/jla-gardner/locache
Keywords: cache,disk
Classifier: License :: OSI Approved :: MIT License
Classifier: Programming Language :: Python
Classifier: Programming Language :: Python :: 3
Requires-Python: >=3.8
License-File: LICENCE.md
Provides-Extra: dev
Requires-Dist: bumpver; extra == "dev"
Requires-Dist: ruff; extra == "dev"
Provides-Extra: publish
Requires-Dist: twine; extra == "publish"
Requires-Dist: build; extra == "publish"
Provides-Extra: tests
Requires-Dist: pytest; extra == "tests"
Requires-Dist: pytest-cov; extra == "tests"
